moodle_to_vikwikiquiz/helpers.py
moodle_to_vikwikiquiz/main.py
moodle_to_vikwikiquiz/py.typed
moodle_to_vikwikiquiz/wiki.py
moodle_to_vikwikiquiz/quiz/grading_types.py
moodle_to_vikwikiquiz/quiz/helpers.py
moodle_to_vikwikiquiz/quiz/quiz.py
moodle_to_vikwikiquiz/quiz/quiz_element.py
moodle_to_vikwikiquiz/quiz/illustrations/illustration.py
moodle_to_vikwikiquiz/quiz/illustrations/state_of_illustrations.py
moodle_to_vikwikiquiz/quiz/questions/helpers.py
moodle_to_vikwikiquiz/quiz/questions/question.py
moodle_to_vikwikiquiz/quiz/questions/question_types.py
moodle_to_vikwikiquiz/quiz/questions/answers/answer.py
moodle_to_vikwikiquiz/quiz/questions/answers/helpers.py
moodle_to_vikwikiquiz-2.1.0.dist-info/METADATA
moodle_to_vikwikiquiz-2.1.0.dist-info/WHEEL
moodle_to_vikwikiquiz-2.1.0.dist-info/entry_points.txt
moodle_to_vikwikiquiz-2.1.0.dist-info/top_level.txt
moodle_to_vikwikiquiz-2.1.0.dist-info/RECORD
