Metadata-Version: 2.1
Name: moodle-to-vikwikiquiz
Version: 2.1.0
Summary: A CLI for converting graded Moodle quiz HTMLs to a vik.wiki quiz wikitext
Author-email: Máté Gyöngyösi <melees00_quern@icloud.com>
Project-URL: Homepage, https://github.com/gy-mate/moodle-to-vikwikiquiz
Project-URL: Issues, https://github.com/gy-mate/moodle-to-vikwikiquiz/issues
Project-URL: Funding, https://github.com/sponsors/gy-mate
Classifier: Programming Language :: Python :: 3
Classifier: Development Status :: 4 - Beta
Classifier: License :: OSI Approved :: GNU General Public License v3 (GPLv3)
Classifier: Operating System :: OS Independent
Classifier: Typing :: Typed
Classifier: Intended Audience :: Education
Requires-Python: >=3.12
Requires-Dist: beautifulsoup4 ==4.13.5
Requires-Dist: plum-dispatch ==2.5.7
Requires-Dist: pylatexenc ==2.10
Requires-Dist: pyperclip ==1.10.0
Requires-Dist: Send2Trash ==1.8.3
Provides-Extra: dev
Requires-Dist: black ==25.9.0 ; extra == 'dev'
Requires-Dist: mypy ==1.18.2 ; extra == 'dev'
Requires-Dist: types-beautifulsoup4 ==4.12.0.20250516 ; extra == 'dev'
